pyfileflow/__init__.py
pyfileflow/ppath.py
pyfileflow/rule.py
pyfileflow/utils.py
pyfileflow-1.0.4.dist-info/LICENSE
pyfileflow-1.0.4.dist-info/METADATA
pyfileflow-1.0.4.dist-info/WHEEL
pyfileflow-1.0.4.dist-info/RECORD
