Metadata-Version: 2.1
Name: pyfileflow
Version: 1.0.4
Summary: PyFileFlow is a Python module that organizes files in designated folders based on user-defined rules, simplifying file management tasks and maintaining a tidy file system.
License: GPL-2.0-or-later
Author: Antonin HENON
Author-email: antonin.henon@outlook.fr
Requires-Python: >=3.11,<4.0
Classifier: License :: OSI Approved :: GNU General Public License v2 or later (GPLv2+)
Classifier: Programming Language :: Python :: 3
Classifier: Programming Language :: Python :: 3.11
Requires-Dist: typing-extensions (>=4.7.1,<5.0.0)
